LICENSE
README.md
setup.py
dm_gym/__init__.py
dm_gym/create_env.py
dm_gym/env_conf.py
dm_gym/version.py
dm_gym.egg-info/PKG-INFO
dm_gym.egg-info/SOURCES.txt
dm_gym.egg-info/dependency_links.txt
dm_gym.egg-info/not-zip-safe
dm_gym.egg-info/requires.txt
dm_gym.egg-info/top_level.txt
dm_gym/envs/__init__.py
dm_gym/envs/register.py
dm_gym/envs/classification/__init__.py
dm_gym/envs/classification/classification_env_v0.py
dm_gym/envs/clustering/__init__.py
dm_gym/envs/clustering/clustering_env_v0.py
dm_gym/envs/clustering/clustering_env_v1.py
dm_gym/envs/clustering/clustering_env_v2.py
dm_gym/envs/clustering/clustering_env_v3.py
dm_gym/rewards/ClassificationEnv_0_reward.py
dm_gym/rewards/ClusteringEnv_0_reward.py
dm_gym/rewards/ClusteringEnv_1_reward.py
dm_gym/rewards/ClusteringEnv_2_reward.py
dm_gym/rewards/ClusteringEnv_3_reward.py
dm_gym/rewards/__init__.py
dm_gym/utils/__init__.py
dm_gym/utils/data_gen.py
dm_gym/utils/livegraph.py